{
  "project_info": {
    "project_number": "259454430568",
    "project_id": "fluttertwitch",
    "storage_bucket": "fluttertwitch.appspot.com"
  },
  "client": [
    {
      "client_info": {
        "mobilesdk_app_id": "1:259454430568:android:8029bff9eeb6632d7dbadd",
        "android_client_info": {
          "package_name": "com.app.flutter_twitch"
        }
      },
      "oauth_client": [
        {
          "client_id": "259454430568-0n9g6tde4ogg9s9lt73gs5sit8rcoc5b.apps.googleusercontent.com",
          "client_type": 1,
          "android_info": {
            "package_name": "com.app.flutter_twitch",
            "certificate_hash": "d06e70733e923c98303bea92cbf660e16a868124"
          }
        },
        {
          "client_id": "259454430568-7fs744mkm0cah89m1m2k103402edpa37.apps.googleusercontent.com",
          "client_type": 3
        }
      ],
      "api_key": [
        {
          "current_key": "AIzaSyA6T8laIfPqOgsmiKPu8hr7_vLUya9qGcA"
        }
      ],
      "services": {
        "appinvite_service": {
          "other_platform_oauth_client": [
            {
              "client_id": "259454430568-7fs744mkm0cah89m1m2k103402edpa37.apps.googleusercontent.com",
              "client_type": 3
            }
          ]
        }
      }
    }
  ],
  "configuration_version": "1"
}